{
  "id": "southeast_asia_sigbin",
  "sheet": "Southeast_Asia",
  "region": "Southeast_Asia",
  "name": "Sigbin",
  "type": "Monster",
  "cultureRegion": "Philippines",
  "domainRole": "Goatlike, Stealth",
  "shortLoreBlurb": "Backwards-walking creature that drinks shadows and blood.",
  "overlapsLinks": "",
  "tags": "Monster",
  "status": ",",
  "impact": ",",
  "confidenceBeliefLevel": ",",
  "clusterTheme": ",",
  "mediaPopLinks": ",",
  "yearTimeline": ",",
  "primarySource": ",",
  "reference": ",",
  "imageName": "Sigbin",
  "attack": 0,
  "defense": 0,
  "imageAssetPath": "assets/images/placeholders/card_placeholder.png",
  "description": "Backwards-walking creature that drinks shadows and blood.",
  "ownedCount": 0
}