{
  "id": "south_america_ao_ao",
  "sheet": "South_America",
  "region": "South_America",
  "name": "Ao Ao",
  "type": "Monster",
  "cultureRegion": "Guarani",
  "domainRole": "Man-eating sheep beast",
  "shortLoreBlurb": "Malevolent",
  "overlapsLinks": "Herd predator",
  "tags": ",",
  "status": ",",
  "impact": ",",
  "confidenceBeliefLevel": ",",
  "clusterTheme": ",",
  "mediaPopLinks": ",",
  "yearTimeline": ",",
  "primarySource": ",",
  "reference": ",",
  "imageName": "Ao Ao",
  "attack": 0,
  "defense": 0,
  "imageAssetPath": "assets/images/placeholders/card_placeholder.png",
  "description": "Malevolent",
  "ownedCount": 0
}