{
  "id": "central_africa_mbundu_ancestors",
  "sheet": "Central_Africa",
  "region": "Central_Africa",
  "name": "Mbundu Ancestors",
  "type": "Spirits",
  "cultureRegion": "Angola (Mbundu)",
  "domainRole": "Royal Ancestors, Oaths",
  "shortLoreBlurb": "Mbundu Ancestors is a spirits from Angola (Mbundu) associated with royal ancestors, oaths.",
  "overlapsLinks": ",",
  "tags": "Spirit",
  "status": ",",
  "impact": ",",
  "confidenceBeliefLevel": ",",
  "clusterTheme": ",",
  "mediaPopLinks": ",",
  "yearTimeline": ",",
  "primarySource": ",",
  "reference": ",",
  "imageName": "Mbundu Ancestors",
  "attack": 0,
  "defense": 0,
  "imageAssetPath": "assets/images/placeholders/card_placeholder.png",
  "description": "Mbundu Ancestors is a spirits from Angola (Mbundu) associated with royal ancestors, oaths.",
  "ownedCount": 0
}