{
  "id": "central_africa_kalunga_line",
  "sheet": "Central_Africa",
  "region": "Central_Africa",
  "name": "Kalunga (Line)",
  "type": "Principle/Deity",
  "cultureRegion": "Kongo",
  "domainRole": "Sea of the Dead, Threshold",
  "shortLoreBlurb": "Kalunga (Line) is a principle/deity from Kongo associated with sea of the dead, threshold. Appeased for safe passage and rains.",
  "overlapsLinks": "Manannán (Celtic), Naga (India/SE Asia), Poseidon (Greek), Tangaroa (Polynesia), Yemaya (Yoruba)",
  "tags": "Deity, Water Spirit",
  "status": ",",
  "impact": ",",
  "confidenceBeliefLevel": ",",
  "clusterTheme": ",",
  "mediaPopLinks": ",",
  "yearTimeline": ",",
  "primarySource": ",",
  "reference": ",",
  "imageName": "Kalunga (Line)",
  "attack": 0,
  "defense": 0,
  "imageAssetPath": "assets/images/placeholders/card_placeholder.png",
  "description": "Kalunga (Line) is a principle/deity from Kongo associated with sea of the dead, threshold. Appeased for safe passage and rains.",
  "ownedCount": 0
}