{
  "id": "india_arjuna",
  "sheet": "India",
  "region": "India",
  "name": "Arjuna",
  "type": "Hero",
  "cultureRegion": "India (Hindu)",
  "domainRole": "Archery, Dharma",
  "shortLoreBlurb": "Arjuna is a hero from India (Hindu) associated with archery, dharma.",
  "overlapsLinks": ",",
  "tags": "Hero",
  "status": ",",
  "impact": ",",
  "confidenceBeliefLevel": ",",
  "clusterTheme": ",",
  "mediaPopLinks": ",",
  "yearTimeline": ",",
  "primarySource": ",",
  "reference": ",",
  "imageName": "Arjuna",
  "attack": 0,
  "defense": 0,
  "imageAssetPath": "assets/images/placeholders/card_placeholder.png",
  "description": "Arjuna is a hero from India (Hindu) associated with archery, dharma.",
  "ownedCount": 0
}