{
  "id": "north_africa_egypt_maghreb_qetesh_qadesh",
  "sheet": "North Africa (Egypt & Maghreb)",
  "region": "North Africa (Egypt & Maghreb)",
  "name": "Qetesh (Qadesh)",
  "type": "Deity/Sync.",
  "cultureRegion": "Egypt/Levant",
  "domainRole": "Love, Fertility",
  "shortLoreBlurb": "Qetesh (Qadesh) is a deity/sync. from Egypt/Levant associated with love, fertility.",
  "overlapsLinks": ",",
  "tags": "Deity, Fertility/Love",
  "status": ",",
  "impact": ",",
  "confidenceBeliefLevel": ",",
  "clusterTheme": ",",
  "mediaPopLinks": ",",
  "yearTimeline": ",",
  "primarySource": ",",
  "reference": ",",
  "imageName": "Qetesh (Qadesh)",
  "attack": 0,
  "defense": 0,
  "imageAssetPath": "assets/images/placeholders/card_placeholder.png",
  "description": "Qetesh (Qadesh) is a deity/sync. from Egypt/Levant associated with love, fertility.",
  "ownedCount": 0
}