{
  "id": "steppe_siberia_albasty_alvasti",
  "sheet": "Steppe_Siberia",
  "region": "Steppe_Siberia",
  "name": "Albasty (Alvasti)",
  "type": "Demon",
  "cultureRegion": "Turkic Steppe",
  "domainRole": "Female Demon, Illness",
  "shortLoreBlurb": "Albasty (Alvasti) is a demon from Turkic Steppe tied to female demon, illness.",
  "overlapsLinks": "",
  "tags": "Monster",
  "status": ",",
  "impact": ",",
  "confidenceBeliefLevel": ",",
  "clusterTheme": ",",
  "mediaPopLinks": ",",
  "yearTimeline": ",",
  "primarySource": ",",
  "reference": ",",
  "imageName": "Albasty (Alvasti)",
  "attack": 0,
  "defense": 0,
  "imageAssetPath": "assets/images/placeholders/card_placeholder.png",
  "description": "Albasty (Alvasti) is a demon from Turkic Steppe tied to female demon, illness.",
  "ownedCount": 0
}