{
  "id": "steppe_siberia_it_gen_eke",
  "sheet": "Steppe_Siberia",
  "region": "Steppe_Siberia",
  "name": "Itügen Eke",
  "type": "Deity",
  "cultureRegion": "Mongolic",
  "domainRole": "Earth Mother, Pastures",
  "shortLoreBlurb": "Old earth goddess of the steppe; contracts broken bring drought.",
  "overlapsLinks": "",
  "tags": "Deity, Warrior/Protector",
  "status": ",",
  "impact": ",",
  "confidenceBeliefLevel": ",",
  "clusterTheme": ",",
  "mediaPopLinks": ",",
  "yearTimeline": ",",
  "primarySource": ",",
  "reference": ",",
  "imageName": "Itügen Eke",
  "attack": 0,
  "defense": 0,
  "imageAssetPath": "assets/images/placeholders/card_placeholder.png",
  "description": "Old earth goddess of the steppe; contracts broken bring drought.",
  "ownedCount": 0
}