{
  "id": "west_africa_asase_yaa",
  "sheet": "West Africa",
  "region": "West Africa",
  "name": "Asase Yaa",
  "type": "Deity",
  "cultureRegion": "Akan",
  "domainRole": "Earth, Fertility, Truth",
  "shortLoreBlurb": "Asase Yaa is a deity from Akan associated with earth, fertility, truth.",
  "overlapsLinks": ",",
  "tags": "Deity, Fertility/Love",
  "status": ",",
  "impact": ",",
  "confidenceBeliefLevel": ",",
  "clusterTheme": ",",
  "mediaPopLinks": ",",
  "yearTimeline": ",",
  "primarySource": ",",
  "reference": ",",
  "imageName": "Asase Yaa",
  "attack": 0,
  "defense": 0,
  "imageAssetPath": "assets/images/placeholders/card_placeholder.png",
  "description": "Asase Yaa is a deity from Akan associated with earth, fertility, truth.",
  "ownedCount": 0
}