{
  "id": "west_africa_bori_spirits",
  "sheet": "West Africa",
  "region": "West Africa",
  "name": "Bori Spirits",
  "type": "Spirits",
  "cultureRegion": "Hausa",
  "domainRole": "Possession Cult, Healing",
  "shortLoreBlurb": "Bori Spirits is a spirits from Hausa associated with possession cult, healing.",
  "overlapsLinks": ",",
  "tags": "Spirit",
  "status": ",",
  "impact": ",",
  "confidenceBeliefLevel": ",",
  "clusterTheme": ",",
  "mediaPopLinks": ",",
  "yearTimeline": ",",
  "primarySource": ",",
  "reference": ",",
  "imageName": "Bori Spirits",
  "attack": 0,
  "defense": 0,
  "imageAssetPath": "assets/images/placeholders/card_placeholder.png",
  "description": "Bori Spirits is a spirits from Hausa associated with possession cult, healing.",
  "ownedCount": 0
}