{
  "id": "west_africa_egbe_run_spirit_peers",
  "sheet": "West Africa",
  "region": "West Africa",
  "name": "Egbe Òrun (Spirit Peers)",
  "type": "Spirits/Class",
  "cultureRegion": "Yoruba",
  "domainRole": "Destiny Companions, Dreams",
  "shortLoreBlurb": "Egbe Òrun (Spirit Peers) is a spirits/class from Yoruba associated with destiny companions, dreams.",
  "overlapsLinks": ",",
  "tags": "Spirit",
  "status": ",",
  "impact": ",",
  "confidenceBeliefLevel": ",",
  "clusterTheme": ",",
  "mediaPopLinks": ",",
  "yearTimeline": ",",
  "primarySource": ",",
  "reference": ",",
  "imageName": "Egbe Òrun (Spirit Peers)",
  "attack": 0,
  "defense": 0,
  "imageAssetPath": "assets/images/placeholders/card_placeholder.png",
  "description": "Egbe Òrun (Spirit Peers) is a spirits/class from Yoruba associated with destiny companions, dreams.",
  "ownedCount": 0
}