{
  "id": "tibet_nepal_yeti",
  "sheet": "Tibet & Nepal",
  "region": "Tibet & Nepal",
  "name": "Yeti",
  "type": "Cryptid",
  "cultureRegion": "Tibet/Himalayas",
  "domainRole": "Wild Man, Snow",
  "shortLoreBlurb": "Yeti is a cryptid from Tibet/Himalayas associated with wild man, snow.",
  "overlapsLinks": "",
  "tags": "Monster",
  "status": ",",
  "impact": ",",
  "confidenceBeliefLevel": ",",
  "clusterTheme": ",",
  "mediaPopLinks": ",",
  "yearTimeline": ",",
  "primarySource": ",",
  "reference": ",",
  "imageName": "Yeti",
  "attack": 0,
  "defense": 0,
  "imageAssetPath": "assets/images/placeholders/card_placeholder.png",
  "description": "Yeti is a cryptid from Tibet/Himalayas associated with wild man, snow.",
  "ownedCount": 0
}