{
  "id": "southern_africa_modjadji_rain_queen",
  "sheet": "Southern_Africa",
  "region": "Southern_Africa",
  "name": "Modjadji (Rain Queen)",
  "type": "Heroine/Deity",
  "cultureRegion": "Balobedu (Limpopo)",
  "domainRole": "Rainmaking, Sovereignty",
  "shortLoreBlurb": "Modjadji (Rain Queen) is a heroine/deity from Balobedu (Limpopo) associated with rainmaking, sovereignty. Appeased for safe passage and rains.",
  "overlapsLinks": "Manannán (Celtic), Naga (India/SE Asia), Poseidon (Greek), Tangaroa (Polynesia), Yemaya (Yoruba)",
  "tags": "Deity, Hero, Water Spirit",
  "status": ".",
  "impact": ",",
  "confidenceBeliefLevel": ",",
  "clusterTheme": ",",
  "mediaPopLinks": ",",
  "yearTimeline": ",",
  "primarySource": ",",
  "reference": ",",
  "imageName": "Modjadji (Rain Queen)",
  "attack": 0,
  "defense": 0,
  "imageAssetPath": "assets/images/placeholders/card_placeholder.png",
  "description": "Modjadji (Rain Queen) is a heroine/deity from Balobedu (Limpopo) associated with rainmaking, sovereignty. Appeased for safe passage and rains.",
  "ownedCount": 0
}