{
  "id": "north_america_momo_missouri_monster",
  "sheet": "North America",
  "region": "North_America",
  "name": "Momo (Missouri Monster)",
  "type": "Cryptid",
  "cultureRegion": "Missouri",
  "domainRole": "Hairy hominid, River bluffs",
  "shortLoreBlurb": "A shaggy, skunky bigfoot cousin haunting the Mississippi palisades.",
  "overlapsLinks": "Sasquatch (NA), Yeti (Himalayas)",
  "tags": "Monster",
  "status": ",",
  "impact": ",",
  "confidenceBeliefLevel": ",",
  "clusterTheme": ",",
  "mediaPopLinks": ",",
  "yearTimeline": ",",
  "primarySource": ",",
  "reference": ",",
  "imageName": "Momo (Missouri Monster)",
  "attack": 0,
  "defense": 0,
  "imageAssetPath": "assets/images/placeholders/card_placeholder.png",
  "description": "A shaggy, skunky bigfoot cousin haunting the Mississippi palisades.",
  "ownedCount": 0
}